{
  "id": "ufp_smart_detection",
  "title": {
    "en": "A smart detection event",
    "nl": "Een slim detectie event"
  },
  "tokens": [
    {
      "name": "ufp_smart_detection_camera",
      "type": "string",
      "title": {
        "en": "Camera",
        "nl": "Camera"
      },
      "example": {
        "en": "Doorbell",
        "nl": "Deurbel"
      }
    },
    {
      "name": "smart_detection_type",
      "type": "string",
      "title": {
        "en": "Smart detection type",
        "nl": "Slim detectie type"
      },
      "example": {
        "en": "vehicle",
        "nl": "vehicle"
      }
    },
    {
      "name": "score",
      "type": "number",
      "title": {
        "en": "Score",
        "nl": "Score"
      },
      "example": {
        "en": "62",
        "nl": "62"
      }
    }
  ]
}